bangla_stemmer/__init__.py
bangla_stemmer/resources/__init__.py
bangla_stemmer/resources/grammar.py
bangla_stemmer/stemmer/__init__.py
bangla_stemmer/stemmer/stemmer.py
bangla_stemmer-1.0.dist-info/LICENSE
bangla_stemmer-1.0.dist-info/METADATA
bangla_stemmer-1.0.dist-info/WHEEL
bangla_stemmer-1.0.dist-info/top_level.txt
bangla_stemmer-1.0.dist-info/RECORD
