Metadata-Version: 2.1
Name: bangla-stemmer
Version: 1.0
Summary: A Python package to get stem of any inflected Bangla words.
Home-page: https://github.com/Fatick-DevStudio/Bangla-stemmer
Author: Mezbaul Islam Protick
Author-email: mezbaulislamprotick@gmail.com
License: Apache 2.0
Keywords: bengali,bangla,stemmer,bengali stemmer,bangla stemmer
Platform: UNKNOWN
Classifier: Development Status :: 4 - Beta
Classifier: License :: OSI Approved :: Apache Software License
Classifier: Programming Language :: Python :: 3
Classifier: Programming Language :: Python :: 3.6
Classifier: Programming Language :: Python :: 3.7
